XorSalsa8.v
`timescale 1ns/1ns 

/* Небольшое пояснение по идее проекта. Разумеется 99 из 100 стали бы это делать 
 * на блочной памяти. И от меня наверняка ожидали того же самого. Но во-первых мы не
 * ищем лёгких путей. Хотелось продемонстрировать действительно красивый алгоритм.
 * Я вообще очень люблю сдвиговые регистры, стеки и т.п. Во-вторых в ряде ситуаций
 * такое решение может быть и вполне практичным. Например почти во всех проектах 
 * которые я делал, блочная память была на вес золота. Кроме последнего, там наоборот
 * памяти было залейся, но дико не хватало логики. Так что изыскивать меры по её 
 * экономии безусловно стоит. Тем более сдвиговый регистр штука недорогая. Насколько я
 * помню(спорить сейчас не берусь), у Xilinx одноразрядный сдвиговый регистр длинной
 * до 16, обходится в одну ячейку. Если же говорить о реализации в заказной микросхеме,
 * там стоимость сдвигового регистра и полноценной памяти вообще вещи несопоставимые.
 * 
 * По быстродействию. Скажу сразу. Конвейеризовать я даже не пытался. Не пытался даже 
 * синтезировать. Писалось второпях, скорей-скорей. Ещё кучу времени потратил пока не 
 * сдался, пытаясь заставить работать ghdl(я его всё-таки добью, но потом, в более 
 * спокойной обстановке). 
 * Как бы то ни было, критический путь тут вполне понятен. Это от выхода до входа 
 * сдвигового регистра через функцию R. Там мультиплексор выбора шины, потом
 * сложение, потом мультиплексор выбора сдвига, потом or, потом xor. Набегает конечно
 * не слишком много, но и немало. С конвейеризацией этой операции возможны проблемы.
 * Внеси сюда конвейерную задержку, вся красивая сдвиговая схема рассыплется. Правда 
 * есть мысль. Конвейерная задержка должна быть равна ровно 4. Тогда есть шанс всё 
 * снова собрать. А 4 регистра в такой схеме более чем достаточно. Правда разумеется
 * на практике я этого не проверял. 
 */


module l_shift(  //левый сдвиговый регистр, с задаваемыми размером(size) и шириной шины(width)
	input clk,				//клок
	input enb,				//разрешение сдвига
	input rot,              //циклический сдвиг
	input[width-1:0] si,    //вход
	output[width-1:0] l,	//левый выход
	output[width-1:0] r		//правый выход
	);
	parameter size=4, width=32;

	reg[width-1:0] rr[size-1:0];
	integer i;
	always @(posedge clk)
		if(enb) begin
			if(rot) rr[size-1]<=l;
			else    rr[size-1]<=si;
			for(i=size-1; i>0; i=i-1)
				rr[i-1]<=rr[i];
			end
			
	assign l=rr[0];
	assign r=rr[size-1]; 
endmodule			

module lr_shift(  //двунаправленный сдвиговый регистр, с задаваемыми размером(size) и шириной шины(width)
	input clk,				//клок
	input enb,				//разрешение сдвига
	input dir,				//направление: 0 - влево, 1 - вправо
	input rot,              //циклический сдвиг
	input[width-1:0] si,    //вход
	output[width-1:0] l,	//левый выход
	output[width-1:0] r		//правый выход
	);
	parameter size=4, width=32;

	reg[width-1:0] rr[size-1:0];
	integer i;
	always @(posedge clk)
		if(enb)
			if(dir) begin
				if(rot) rr[0]<=r;
				else    rr[0]<=si;
				for(i=0; i<size-1; i=i+1)
					rr[i+1]<=rr[i]; 
			end
			else begin
				if(rot) rr[size-1]<=l;
				else    rr[size-1]<=si;
				for(i=size-1; i>0; i=i-1)
					rr[i-1]<=rr[i];
			end
		
	assign l=rr[0];
	assign r=rr[size-1];
endmodule			

module rfunc(     //Функция R
	input[31:0] v,
	input[31:0] u1,
	input[31:0] u2,
	input[1:0] s,
	output[31:0] vv
);
	wire[31:0] w=u1+u2;
	wire[31:0] w7=(w<<7)   | (w>>(32-7));
	wire[31:0] w9=(w<<9)   | (w>>(32-9));
	wire[31:0] w13=(w<<13) | (w>>(32-13));
	wire[31:0] w18=(w<<18) | (w>>(32-18));
	reg[31:0] uu;
	
	always @*
		case (s)
			2'b00: uu=w7;
			2'b01: uu=w9;
			2'b10: uu=w13;
			2'b11: uu=w18;
		endcase	
	assign vv=uu^v;
endmodule
	
				
module XorSalsa8( //требуемое устройство
	input clk,			//клок
	input rst,			//сброс
	input bx,			//выбор констант (1) или данных(0)
	input wr,			//запись
	input rd,			//чтение
	input enc,			//кодирование
	input[31:0]  di, 	//входная шина данных
	output[31:0] do,	//выходная шина данных
	output rdy			//готовность кодирования
);


	//Внутренние компоненты
	reg b_enb, bx_enb, b_rot, bx_rot;
	reg[3:0] ss_enb, ss_rot; 
	
	reg[1:0] dir;
	reg[31:0] b_si, ss_si; //для bx si подключен прямо к входной шине, для всех ss_ui входы общие
	wire[31:0] b_l, bx_l, l0, l1, l2, l3;
	reg[1:0] rs;
	reg[31:0] rv, ru1, ru2;
	wire[31:0] rvv; 
	
	l_shift  #(16, 32) rr_b ( //регистр данных
		.clk	(clk),
		.enb	(b_enb),
		.rot	(b_rot),
		.si		(b_si),
		.l		(b_l)
	);
	l_shift  #(16, 32) rr_bx  ( //регистр констант
		.clk	(clk),
		.enb	(bx_enb),
		.rot	(bx_rot),
		.si		(di),
		.l		(bx_l)
	);
	l_shift #(4, 32) ss_u0 ( //операционный регистр u0
		.clk	(clk),
		.enb	(ss_enb[0]),
		.rot	(ss_rot[0]),
		.si		(ss_si),
		.l		(l0)		
	);
	lr_shift #(4, 32) ss_u1 ( //операционный регистр u1
		.clk	(clk),
		.enb	(ss_enb[1]),
		.dir	(dir[0]),
		.rot	(ss_rot[1]),
		.si		(ss_si),
		.l		(l1)		
	);
	l_shift #(4, 32) ss_u2 ( //операционный регистр u2
		.clk	(clk),
		.enb	(ss_enb[2]),
		.rot	(ss_rot[2]),
		.si		(ss_si),
		.l		(l2)		
	);
	lr_shift #(4, 32) ss_u3 ( //операционный регистр u3
		.clk	(clk),
		.enb	(ss_enb[3]),
		.dir	(dir[1]),
		.rot	(ss_rot[3]),
		.si		(ss_si),
		.l		(l3)		
	);
	rfunc rfunc(
		.v	(rv),
		.u1 (ru1),
		.u2	(ru2),
		.s	(rs),
		.vv (rvv)
	);
	
	
	//Режим работы устройства.
	//Устройство работает в двух режимах - ввода/вывода и кодирования
	reg ioenc;    //1 - ввод/вывод, 0 - кодирование
	reg enc_end;  //сигнал окончания кодирования
	always @(posedge clk)
		if(rst|enc_end) ioenc<=1;
		else 
			if(enc) ioenc<=0;

	//------------------- Режим ввода/вывода ----------------------------------//
	
	reg iwr, ird, ienc, wr0, rd0, enc0;  //выделяем сигналы чтения/записи в 1 такт
	always @(posedge clk)
	begin
		rd0<=rd;
		wr0<=wr;
		enc0<=enc;
	end
	always @*
	begin
		if(rd&(!rd0)) ird=ioenc;  else ird=0;
		if(wr&(!wr0)) iwr=ioenc;  else iwr=0;	
		ienc=enc&(!enc0);
	end	
	
	//Счетчик чтения-записи
	reg[3:0] iocnt;
	reg b_rwop;     //операция с регистром данных
	always @(posedge clk)
		if(rst==1) iocnt<=4'h0;
		else
			if(b_rwop)
				iocnt<=iocnt+1; //считает только данные, но не константы
	always @*
		if(ioenc&(!bx)) b_rwop=iwr|ird; //чтение или запись в режиме io при низком bx
		else b_rwop=0;
		
	//Сигналы режима ввода-вывода
	reg[3:0] io_enb, io_rot;
	reg[31:0] ss_o; //выход регистров ss_u, участвующий в формировании выходной шины
	reg[31:0] io_si;
	reg[31:0] d_out; //выход
	always @*
	begin
		b_si=di ^ bx_l;       //это пишется в регистр данных и операционные регистры
		io_si=b_si;
		bx_enb=iwr|ird;         //bx сдвигается при любых операциях чтения-записи
		bx_rot=(!bx)|rd;        //и циклится при операциях с b и любых чтениях
		b_enb=(iwr|ird)&(!bx);  //b сдвигается при чтении и записи если bx низкий
		b_rot=bx|rd|(!wr);      //b циклится при чтении, операциях с bx и при низком wr
		io_rot={4{b_rot}};
		
		case(iocnt)
			4'd0, 4'd5, 4'd10, 4'd15: begin
				if(b_enb) io_enb=4'b0001; else io_enb=4'd0;
				ss_o=l0;
			end
			4'd1, 4'd6, 4'd11, 4'd12: begin
				if(b_enb) io_enb=4'b0010; else io_enb=4'd0;
				ss_o=l1;
			end
			4'd2, 4'd7, 4'd8,  4'd13: begin
				if(b_enb) io_enb=4'b0100; else io_enb=4'd0;
				ss_o=l2;
			end
			4'd3, 4'd4, 4'd9,  4'd14: begin
				if(b_enb) io_enb=4'b1000; else io_enb=4'd0;
				ss_o=l3;
			end
		endcase
		if(bx) d_out=bx_l; else d_out=ss_o+b_l;
		//if(rd) ss_rot=4'd15; else ss_rot=4'd0;
	end
	
	//----------------------------- Режим кодирования ---------------------------//
	reg[1:0] encnt4;    //счетчик циклов
	reg[4:0] encnt34;   //счётчик на 34 для внутреннего цикла
	reg enc34_1;        //дополнительный бит счётчика для формирования паузы
	reg pause;          //пауза
	reg enc_eoc;		//конец цикла
	//введение паузы непосредственно в счетчик сильно облегчает управление устройством.
	always @(posedge clk)
		if(rst) encnt34<=5'd31;
		else
		if(ienc) encnt34<=5'd0;
		else
		if(!ioenc)
			if(encnt34[3:0]==4'd0) encnt34<=encnt34+enc34_1;
			else
			if(!enc_end)
				encnt34<=encnt34+1;
		
	always @(posedge clk) 
		if(ienc|rst) encnt4<=2'd0;
		else
		if(enc_eoc) encnt4=encnt4+1;
	
	always @(posedge clk) //тут формируется пауза в 1 такт в начале и середине цикла
		if(ienc|encnt34[2]|rst) enc34_1<=0;
		else
		if(encnt34[3:0]==4'd0) enc34_1<=1;
		
	always @* begin
		if((enc34_1==0)&&(encnt34[3:0]==0)) pause=1; else pause=0;
		if(encnt34==5'd31) enc_eoc=1; else enc_eoc=0;
		if((encnt34==5'd31)&&(encnt4==2'd3)) enc_end=1; else enc_end=0;
	end
	
	//сигналы управления сдвиговыми регистрами
	reg[3:0] enc_enb, enc_enb1, enc_enb2;
	reg[3:0] enc_rot, enc_rot1, enc_rot2;
	reg[1:0] enc_dir; 
	
	//регулярные сигналы и шины устройства R
	always @*
	begin
		rs=encnt34[3:2];
		case (encnt34[4:2])
			3'd0: begin //R(3, 0, 1);
				rv=l3; ru1=l0; ru2=l1;
				enc_enb1=4'b1011; enc_rot1=4'b0111;
			end
			3'd1: begin //R(2, 3, 0);
				rv=l2; ru1=l3; ru2=l0;
				enc_enb1=4'b1101; enc_rot1=4'b1011;
			end
			3'd2: begin //R(1, 2, 3);
				rv=l1; ru1=l2; ru2=l3;
				enc_enb1=4'b1110; enc_rot1=4'b1101;
			end
			3'd3: begin	//R(0, 1, 2);
				rv=l0; ru1=l1; ru2=l2;
				enc_enb1=4'b0111; enc_rot1=4'b1110;
			end
			3'd4: begin	//R(1, 0, 3);
				rv=l1; ru1=l0; ru2=l3;
				enc_enb1=4'b1011; enc_rot1=4'b1101;
			end
			3'd5: begin //R(2, 1, 0);
				rv=l2; ru1=l1; ru2=l0;
				enc_enb1=4'b0111; enc_rot1=4'b1011;
			end
			3'd6: begin	//R(3, 2, 1);
				rv=l3; ru1=l2; ru2=l1;
				enc_enb1=4'b1110; enc_rot1=4'b0111;
			end
			3'd7: begin	//R(0, 3, 2);
				rv=l0; ru1=l3; ru2=l2;
				enc_enb1=4'b1101; enc_rot1=4'b1110;
			end
		
		endcase
	end
	
	//Сигналы режима кодирования
	always @* begin
		if(encnt34[3:0]==0) begin
			enc_enb2=enc_enb1 | 4'b0100;  //сразу после паузы ещё на один такт сдвигается u2 
			enc_rot2=enc_rot1 | 4'b0100;
		end
		else begin
			enc_enb2=enc_enb1; 
			enc_rot2=enc_rot1;
		end
		if(pause) begin
			enc_dir[0]=~encnt34[4];
			enc_dir[1]=encnt34[4];
			enc_enb=4'b1110;
			enc_rot=4'b1110;
		end
		else begin
			enc_dir=2'b00;
			enc_enb=enc_enb2;
			enc_rot=enc_rot2;
		end
	end
				
	//Мультиплексор сигналов, в зависимости от режима
	always @*
		if(ioenc) begin //режим ввода-вывода
			ss_si=io_si;
			ss_enb=io_enb;
			ss_rot=io_rot;
			dir=2'b0;
		end
		else begin
			ss_si=rvv;
			ss_enb=enc_enb;
			ss_rot=enc_rot;
			dir=enc_dir;
		end
			
	
	assign rdy=ioenc;
	assign do=d_out;
			
		

endmodule

testbench.v
`timescale 1ns/100ps 
module testbench;
	reg clk;   //общий клок
	always 
		#100 clk=~clk;

	reg rst, bx, wr, rd, enc;
	reg[31:0] di;
	wire rdy;
	wire[31:0] do;
	
	XorSalsa8 test(
		.clk	(clk),
		.rst	(rst),
		.bx		(bx),
		.wr		(wr),
		.rd		(rd),
		.enc	(enc),
		.di		(di),
		.do		(do),
		.rdy	(rdy)
	);
	
	reg[31:0] mem_b   [0:15];
	reg[31:0] mem_bx  [0:15];
	reg[31:0] mem_test [0:15];
	
	
	task loadBx;
		integer i;
		begin
			bx=1;
			rd=0;
			for(i=0; i<16; i++) begin
				di=mem_bx[i];
				wr=1;
				@(posedge clk);
				@(posedge clk);
				wr=0;	
				@(posedge clk);
				@(posedge clk);
			end
		end
	endtask
	
	task loadB;
		integer i;
		begin
			bx=0;
			rd=0;
			for(i=0; i<16; i++) begin
				di=mem_b[i];
				wr=1;
				@(posedge clk);
				@(posedge clk);
				wr=0;	
				@(posedge clk);
				@(posedge clk);
			end
		end
	endtask
	
	task readBlock;
		integer i;
		begin
			wr=0;
			for(i=0; i<16; i++) begin
				rd=1;
				@(posedge clk);
				@(posedge clk);
				rd=0;
				@(posedge clk);
				@(posedge clk);
			end
		end
	endtask
	
	reg[31:0] result;
	reg[31:0] verify;
	reg[31:0] error;
	reg[3:0] number;
	task testBlock;
		integer i;
		begin
			wr=0;
			bx=0;
			verify<=mem_test[0];
			@(posedge clk);
			@(posedge clk);
			for(i=1; i<16; i++) begin
				
				error<=verify^do;
				number<=i;
				rd=1;
				@(posedge clk);
				verify<=mem_test[i];
				@(posedge clk);
				rd=0;
				@(posedge clk);
				@(posedge clk);
			end
		end
	endtask
			
		
		

	task skipClk(integer n); 
	integer i;
	begin
		for(i=0; i<n-1; i=i+1)
			@(posedge clk);
	end
	endtask
	
	initial begin
		$dumpfile("xorsalsa8.vcd");
		$dumpvars(0, testbench);
		$readmemh("./bx.txt", mem_bx);
		$readmemh("./b.txt",  mem_b);
		$readmemh("./out.txt", mem_test);
		clk=0;
		rst=1;
		bx=1;
		rd=0;
		wr=0; 
		enc=0;
		verify=0;
		error=0;
		number=0;
		@(posedge clk);
		@(posedge clk);
		rst=0;
		loadBx;
		
		@(posedge clk);
		@(posedge clk);
		loadB;
		
		@(posedge clk);
		@(posedge clk);
		
		readBlock;
		readBlock;
		
		enc=1;
		@(posedge clk);
		@(posedge clk);
		enc=0;

		@(posedge clk);
		@(posedge clk);
		@(rdy)
		skipClk(10);
		
		testBlock;
		
		
		$finish;	
		
	end	
	

endmodule

xorsalsa8.vcd
$date
	Fri Feb  2 12:15:33 2018
$end
$version
	Icarus Verilog
$end
$timescale
	100ps
$end
$scope module testbench $end
$var wire 1 ! rdy $end
$var wire 32 " do [31:0] $end
$var reg 1 # bx $end
$var reg 1 $ clk $end
$var reg 32 % di [31:0] $end
$var reg 1 & enc $end
$var reg 32 ' error [31:0] $end
$var reg 4 ( number [3:0] $end
$var reg 1 ) rd $end
$var reg 1 * rst $end
$var reg 32 + verify [31:0] $end
$var reg 1 , wr $end
$scope module test $end
$var wire 1 # bx $end
$var wire 1 $ clk $end
$var wire 32 - di [31:0] $end
$var wire 32 . do [31:0] $end
$var wire 1 & enc $end
$var wire 1 ) rd $end
$var wire 1 ! rdy $end
$var wire 1 * rst $end
$var wire 1 , wr $end
$var wire 32 / rvv [31:0] $end
$var wire 32 0 l3 [31:0] $end
$var wire 32 1 l2 [31:0] $end
$var wire 32 2 l1 [31:0] $end
$var wire 32 3 l0 [31:0] $end
$var wire 32 4 bx_l [31:0] $end
$var wire 32 5 b_l [31:0] $end
$var reg 1 6 b_enb $end
$var reg 1 7 b_rot $end
$var reg 1 8 b_rwop $end
$var reg 32 9 b_si [31:0] $end
$var reg 1 : bx_enb $end
$var reg 1 ; bx_rot $end
$var reg 32 < d_out [31:0] $end
$var reg 2 = dir [1:0] $end
$var reg 1 > enc0 $end
$var reg 1 ? enc34_1 $end
$var reg 2 @ enc_dir [1:0] $end
$var reg 4 A enc_enb [3:0] $end
$var reg 4 B enc_enb1 [3:0] $end
$var reg 4 C enc_enb2 [3:0] $end
$var reg 1 D enc_end $end
$var reg 1 E enc_eoc $end
$var reg 4 F enc_rot [3:0] $end
$var reg 4 G enc_rot1 [3:0] $end
$var reg 4 H enc_rot2 [3:0] $end
$var reg 5 I encnt34 [4:0] $end
$var reg 2 J encnt4 [1:0] $end
$var reg 1 K ienc $end
$var reg 4 L io_enb [3:0] $end
$var reg 4 M io_rot [3:0] $end
$var reg 32 N io_si [31:0] $end
$var reg 4 O iocnt [3:0] $end
$var reg 1 P ioenc $end
$var reg 1 Q ird $end
$var reg 1 R iwr $end
$var reg 1 S pause $end
$var reg 1 T rd0 $end
$var reg 2 U rs [1:0] $end
$var reg 32 V ru1 [31:0] $end
$var reg 32 W ru2 [31:0] $end
$var reg 32 X rv [31:0] $end
$var reg 4 Y ss_enb [3:0] $end
$var reg 32 Z ss_o [31:0] $end
$var reg 4 [ ss_rot [3:0] $end
$var reg 32 \ ss_si [31:0] $end
$var reg 1 ] wr0 $end
$scope module rfunc $end
$var wire 2 ^ s [1:0] $end
$var wire 32 _ u1 [31:0] $end
$var wire 32 ` u2 [31:0] $end
$var wire 32 a v [31:0] $end
$var wire 32 b vv [31:0] $end
$var wire 32 c w13 [31:0] $end
$var wire 32 d w18 [31:0] $end
$var wire 32 e w7 [31:0] $end
$var wire 32 f w9 [31:0] $end
$var wire 32 g w [31:0] $end
$var reg 32 h uu [31:0] $end
$upscope $end
$scope module rr_b $end
$var wire 1 $ clk $end
$var wire 1 6 enb $end
$var wire 32 i l [31:0] $end
$var wire 32 j r [31:0] $end
$var wire 1 7 rot $end
$var wire 32 k si [31:0] $end
$var integer 32 l i [31:0] $end
$upscope $end
$scope module rr_bx $end
$var wire 1 $ clk $end
$var wire 1 : enb $end
$var wire 32 m l [31:0] $end
$var wire 32 n r [31:0] $end
$var wire 1 ; rot $end
$var wire 32 o si [31:0] $end
$var integer 32 p i [31:0] $end
$upscope $end
$scope module ss_u0 $end
$var wire 1 $ clk $end
$var wire 1 q enb $end
$var wire 32 r l [31:0] $end
$var wire 32 s r [31:0] $end
$var wire 1 t rot $end
$var wire 32 u si [31:0] $end
$var integer 32 v i [31:0] $end
$upscope $end
$scope module ss_u1 $end
$var wire 1 $ clk $end
$var wire 1 w dir $end
$var wire 1 x enb $end
$var wire 32 y l [31:0] $end
$var wire 32 z r [31:0] $end
$var wire 1 { rot $end
$var wire 32 | si [31:0] $end
$var integer 32 } i [31:0] $end
$upscope $end
$scope module ss_u2 $end
$var wire 1 $ clk $end
$var wire 1 ~ enb $end
$var wire 32 !" l [31:0] $end
$var wire 32 "" r [31:0] $end
$var wire 1 #" rot $end
$var wire 32 $" si [31:0] $end
$var integer 32 %" i [31:0] $end
$upscope $end
$scope module ss_u3 $end
$var wire 1 $ clk $end
$var wire 1 &" dir $end
$var wire 1 '" enb $end
$var wire 32 (" l [31:0] $end
$var wire 32 )" r [31:0] $end
$var wire 1 *" rot $end
$var wire 32 +" si [31:0] $end
$var integer 32 ," i [31:0] $end
$upscope $end
$upscope $end
$scope task loadB $end
$var integer 32 -" i [31:0] $end
$upscope $end
$scope task loadBx $end
$var integer 32 ." i [31:0] $end
$upscope $end
$scope task readBlock $end
$var integer 32 /" i [31:0] $end
$upscope $end
$scope task skipClk $end
$var integer 32 0" i [31:0] $end
$var integer 32 1" n [31:0] $end
$upscope $end
$scope task testBlock $end
$var integer 32 2" i [31:0] $end
$upscope $end
$upscope $end
$enddefinitions $end
#0
$dumpvars
bx 2"
bx 1"
bx 0"
bx /"
bx ."
bx -"
bx ,"
bx +"
x*"
bx )"
bx ("
x'"
x&"
bx %"
bx $"
x#"
bx ""
bx !"
x~
bx }
bx |
x{
bx z
bx y
xx
xw
bx v
bx u
xt
bx s
bx r
xq
bx p
bx o
bx n
bx m
bx l
bx k
bx j
bx i
bx h
bx g
bx f
bx e
bx d
bx c
bx b
bx a
bx `
bx _
bx ^
x]
bx \
bx [
bx Z
bx Y
bx X
bx W
bx V
bx U
xT
xS
0R
0Q
xP
bx O
bx N
b1111 M
bx L
0K
bx J
bx I
bx H
bx G
bx F
xE
xD
bx C
bx B
bx A
bx @
x?
x>
bx =
bx <
0;
0:
bx 9
08
17
06
bx 5
bx 4
bx 3
bx 2
bx 1
bx 0
bx /
bx .
bx -
0,
b0 +
1*
0)
b0 (
b0 '
0&
bx %
0$
1#
bx "
x!
$end
#1000
0w
0&"
1t
1{
1#"
1*"
0q
0x
0~
0'"
b0 =
b1111 [
b0 Y
b0 L
b1110 F
b1101 A
b0 @
b1110 H
b1101 C
b1110 G
b1101 B
b11 U
b11 ^
0D
1E
0S
1!
1P
0>
0]
0T
b0 O
b11111 I
b0 J
0?
1$
#2000
0$
#3000
1:
1R
1,
b111001000 %
b111001000 -
b111001000 o
b0 ."
0*
1$
#4000
0$
#5000
0:
0R
b111001000 n
1]
b0 p
b1 J
1$
#6000
0$
#7000
0,
b10 J
1$
#8000
0$
#9000
0]
1D
b11 J
1$
#10000
0$
#11000
1:
1R
0D
1,
b111001001 %
b111001001 -
b111001001 o
b1 ."
b0 J
1$
#12000
0$
#13000
0:
0R
b111001001 n
1]
b0 p
b1 J
1$
#14000
0$
#15000
0,
b10 J
1$
#16000
0$
#17000
0]
1D
b11 J
1$
#18000
0$
#19000
1:
1R
0D
1,
b111010000 %
b111010000 -
b111010000 o
b10 ."
b0 J
1$
#20000
0$
#21000
0:
0R
b111010000 n
1]
b0 p
b1 J
1$
#22000
0$
#23000
0,
b10 J
1$
#24000
0$
#25000
0]
1D
b11 J
1$
#26000
0$
#27000
1:
1R
0D
1,
b111100011 %
b111100011 -
b111100011 o
b11 ."
b0 J
1$
#28000
0$
#29000
0:
0R
b111100011 n
1]
b0 p
b1 J
1$
#30000
0$
#31000
0,
b10 J
1$
#32000
0$
#33000
0]
1D
b11 J
1$
#34000
0$
#35000
1:
1R
0D
1,
b1000001000 %
b1000001000 -
b1000001000 o
b100 ."
b0 J
1$
#36000
0$
#37000
0:
0R
b1000001000 n
1]
b0 p
b1 J
1$
#38000
0$
#39000
0,
b10 J
1$
#40000
0$
#41000
0]
1D
b11 J
1$
#42000
0$
#43000
1:
1R
0D
1,
b1001000101 %
b1001000101 -
b1001000101 o
b101 ."
b0 J
1$
#44000
0$
#45000
0:
0R
b1001000101 n
1]
b0 p
b1 J
1$
#46000
0$
#47000
0,
b10 J
1$
#48000
0$
#49000
0]
1D
b11 J
1$
#50000
0$
#51000
1:
1R
0D
1,
b1010100000 %
b1010100000 -
b1010100000 o
b110 ."
b0 J
1$
#52000
0$
#53000
0:
0R
b1010100000 n
1]
b0 p
b1 J
1$
#54000
0$
#55000
0,
b10 J
1$
#56000
0$
#57000
0]
1D
b11 J
1$
#58000
0$
#59000
1:
1R
0D
1,
b1100011111 %
b1100011111 -
b1100011111 o
b111 ."
b0 J
1$
#60000
0$
#61000
0:
0R
b1100011111 n
1]
b0 p
b1 J
1$
#62000
0$
#63000
0,
b10 J
1$
#64000
0$
#65000
0]
1D
b11 J
1$
#66000
0$
#67000
1:
1R
0D
1,
b1111001000 %
b1111001000 -
b1111001000 o
b1000 ."
b0 J
1$
#68000
0$
#69000
0:
0R
b1111001000 n
1]
b0 p
b1 J
1$
#70000
0$
#71000
0,
b10 J
1$
#72000
0$
#73000
0]
1D
b11 J
1$
#74000
0$
#75000
1:
1R
0D
1,
b10010100001 %
b10010100001 -
b10010100001 o
b1001 ."
b0 J
1$
#76000
0$
#77000
0:
0R
b10010100001 n
1]
b0 p
b1 J
1$
#78000
0$
#79000
0,
b10 J
1$
#80000
0$
#81000
0]
1D
b11 J
1$
#82000
0$
#83000
1:
1R
0D
1,
b10110110000 %
b10110110000 -
b10110110000 o
b1010 ."
b0 J
1$
#84000
0$
#85000
0:
0R
b10110110000 n
1]
b0 p
b1 J
1$
#86000
0$
#87000
0,
b10 J
1$
#88000
0$
#89000
0]
1D
b11 J
1$
#90000
0$
#91000
1:
1R
0D
1,
b11011111011 %
b11011111011 -
b11011111011 o
b1011 ."
b0 J
1$
#92000
0$
#93000
0:
0R
b11011111011 n
1]
b0 p
b1 J
1$
#94000
0$
#95000
0,
b10 J
1$
#96000
0$
#97000
0]
1D
b11 J
1$
#98000
0$
#99000
1:
1R
0D
1,
b100010001000 %
b100010001000 -
b100010001000 o
b1100 ."
b0 J
1$
#100000
0$
#101000
0:
0R
b100010001000 n
1]
b0 p
b1 J
1$
#102000
0$
#103000
0,
b10 J
1$
#104000
0$
#105000
0]
1D
b11 J
1$
#106000
0$
#107000
1:
1R
0D
1,
b101001011101 %
b101001011101 -
b101001011101 o
b1101 ."
b0 J
1$
#108000
0$
#109000
0:
0R
b101001011101 n
1]
b0 p
b1 J
1$
#110000
0$
#111000
0,
b10 J
1$
#112000
0$
#113000
0]
1D
b11 J
1$
#114000
0$
#115000
1:
1R
0D
1,
b110010000000 %
b110010000000 -
b110010000000 o
b1110 ."
b0 J
1$
#116000
0$
#117000
0:
0R
b110010000000 n
1]
b0 p
b1 J
1$
#118000
0$
#119000
0,
b10 J
1$
#120000
0$
#121000
0]
1D
b11 J
1$
#122000
0$
#123000
1:
1R
0D
1,
b111011110111 %
b111011110111 -
b111011110111 o
b1111 ."
b0 J
1$
#124000
0$
#125000
b111100111111 \
b111100111111 u
b111100111111 |
b111100111111 $"
b111100111111 +"
b111001000 "
b111001000 .
b111001000 <
0:
b111100111111 N
b111100111111 9
b111100111111 k
0R
b111001000 4
b111001000 m
b111011110111 n
1]
b0 p
b1 J
1$
#126000
0$
#127000
0,
b10 J
1$
#128000
0$
#129000
0]
1D
b11 J
1$
#130000
0$
#131000
0D
b10000 ."
b0 J
1$
#132000
0$
#133000
b1 J
1$
#134000
0$
#135000
1q
b1 Y
0t
0{
0#"
0*"
b1 L
16
1:
18
b0 [
b110110011 \
b110110011 u
b110110011 |
b110110011 $"
b110110011 +"
1R
bx "
bx .
bx <
b0 M
07
1;
b110110011 N
b110110011 9
b110110011 k
1,
b1111011 %
b1111011 -
b1111011 o
b0 -"
0#
b10 J
1$
#136000
0$
#137000
0q
0x
06
0:
08
b0 Y
b110110010 \
b110110010 u
b110110010 |
b110110010 $"
b110110010 +"
0R
b0 L
b110110010 N
b110110010 9
b110110010 k
b110110011 j
b111001001 4
b111001001 m
b111001000 n
b110110011 s
1]
b1 O
1D
b0 l
b0 p
b0 v
b11 J
1$
#138000
0$
#139000
1t
1{
1#"
1*"
b1111 [
b1111 M
17
0D
0,
b0 J
1$
#140000
0$
#141000
0]
b1 J
1$
#142000
0$
#143000
1x
b10 Y
0t
0{
0#"
0*"
b10 L
16
1:
18
b0 [
b110110101 \
b110110101 u
b110110101 |
b110110101 $"
b110110101 +"
1R
b0 M
07
b110110101 N
b110110101 9
b110110101 k
1,
b1111100 %
b1111100 -
b1111100 o
b1 -"
b10 J
1$
#144000
0$
#145000
0x
0~
06
0:
08
b0 Y
b110101100 \
b110101100 u
b110101100 |
b110101100 $"
b110101100 +"
0R
b0 L
b110101100 N
b110101100 9
b110101100 k
b110110101 j
b111010000 4
b111010000 m
b111001001 n
b110110101 z
1]
b10 O
1D
b0 l
b0 p
b0 }
b11 J
1$
#146000
0$
#147000
1t
1{
1#"
1*"
b1111 [
b1111 M
17
0D
0,
b0 J
1$
#148000
0$
#149000
0]
b1 J
1$
#150000
0$
#151000
1~
b100 Y
0t
0{
0#"
0*"
b100 L
16
1:
18
b0 [
b110101111 \
b110101111 u
b110101111 |
b110101111 $"
b110101111 +"
1R
b0 M
07
b110101111 N
b110101111 9
b110101111 k
1,
b1111111 %
b1111111 -
b1111111 o
b10 -"
b10 J
1$
#152000
0$
#153000
0~
0'"
06
0:
08
b0 Y
b110011100 \
b110011100 u
b110011100 |
b110011100 $"
b110011100 +"
0R
b0 L
b110011100 N
b110011100 9
b110011100 k
b110101111 j
b111100011 4
b111100011 m
b111010000 n
b110101111 ""
1]
b11 O
1D
b0 l
b0 p
b0 %"
b11 J
1$
#154000
0$
#155000
1t
1{
1#"
1*"
b1111 [
b1111 M
17
0D
0,
b0 J
1$
#156000
0$
#157000
0]
b1 J
1$
#158000
0$
#159000
1'"
b1000 Y
0t
0{
0#"
0*"
b1000 L
16
1:
18
b0 [
b101100111 \
b101100111 u
b101100111 |
b101100111 $"
b101100111 +"
1R
b0 M
07
b101100111 N
b101100111 9
b101100111 k
1,
b10000100 %
b10000100 -
b10000100 o
b11 -"
b10 J
1$
#160000
0$
#161000
0'"
b0 Y
b0 L
06
0:
08
b1010001100 \
b1010001100 u
b1010001100 |
b1010001100 $"
b1010001100 +"
0R
b1010001100 N
b1010001100 9
b1010001100 k
b101100111 j
b1000001000 4
b1000001000 m
b111100011 n
b101100111 )"
1]
b100 O
1D
b0 l
b0 p
b0 ,"
b11 J
1$
#162000
0$
#163000
1t
1{
1#"
1*"
b1111 [
b1111 M
17
0D
0,
b0 J
1$
#164000
0$
#165000
0]
b1 J
1$
#166000
0$
#167000
1'"
b1000 Y
0t
0{
0#"
0*"
b1000 L
16
1:
18
b0 [
b1010000011 \
b1010000011 u
b1010000011 |
b1010000011 $"
b1010000011 +"
1R
b0 M
07
b1010000011 N
b1010000011 9
b1010000011 k
1,
b10001011 %
b10001011 -
b10001011 o
b100 -"
b10 J
1$
#168000
0$
#169000
0q
0'"
06
0:
08
b0 Y
b1011001110 \
b1011001110 u
b1011001110 |
b1011001110 $"
b1011001110 +"
0R
b0 L
b1011001110 N
b1011001110 9
b1011001110 k
b1010000011 j
b1001000101 4
b1001000101 m
b1000001000 n
b1010000011 )"
1]
b101 O
1D
b0 l
b0 p
b0 ,"
b11 J
1$
#170000
0$
#171000
1t
1{
1#"
1*"
b1111 [
b1111 M
17
0D
0,
b0 J
1$
#172000
0$
#173000
0]
b1 J
1$
#174000
0$
